{
  "node_info": {
    "icon": "file:asana.svg",
    "defaults": {
      "name": "Asana Trigger"
    },
    "inputs": [],
    "outputs": [
      "Main"
    ],
    "group": [
      "trigger"
    ],
    "authentication": [
      {
        "name": "asanaApi",
        "required": true,
        "displayOptions": {
          "show": {
            "authentication": [
              "accessToken"
            ]
          }
        }
      },
      {
        "name": "asanaOAuth2Api",
        "required": true,
        "displayOptions": {
          "show": {
            "authentication": [
              "oAuth2"
            ]
          }
        }
      }
    ],
    "loadOptionsMethods": [
      "getWorkspaces",
      "name",
      "value"
    ],
    "eventTriggerDescription": "",
    "activationMessage": "",
    "triggerPanel": {},
    "supportsCORS": false,
    "displayName": "Asana Trigger",
    "name": "asanaTrigger",
    "description": "Starts the workflow when Asana events occur.",
    "subtitle": "",
    "version": "1",
    "node_type": "trigger",
    "webhooks": [
      {
        "name": "default",
        "httpMethod": "POST",
        "responseMode": "onReceived",
        "path": "webhook"
      }
    ]
  },
  "metadata": {
    "node": "n8n-nodes-base.asanaTrigger",
    "nodeVersion": "1.0",
    "codexVersion": "1.0",
    "categories": [
      "Productivity"
    ],
    "resources": {
      "credentialDocumentation": [
        {
          "url": "https://docs.n8n.io/integrations/builtin/credentials/asana/"
        }
      ],
      "primaryDocumentation": [
        {
          "url": "https://docs.n8n.io/integrations/builtin/trigger-nodes/n8n-nodes-base.asanatrigger/"
        }
      ]
    }
  },
  "properties": [
    {
      "displayName": "Authentication",
      "name": "authentication",
      "type": "options",
      "value": "accessToken",
      "default": "accessToken",
      "options": [
        {
          "name": "Access Token",
          "value": "accessToken",
          "displayName": "Access Token"
        },
        {
          "name": "OAuth2",
          "value": "oAuth2",
          "displayName": "Oauth2"
        }
      ]
    },
    {
      "displayName": "Resource",
      "name": "resource",
      "type": "string",
      "description": "The resource ID to subscribe to. The resource can be a task or project.",
      "default": "",
      "required": true
    },
    {
      "displayName": "Workspace Name or ID",
      "name": "workspace",
      "type": "options",
      "description": "The workspace ID the resource is registered under. This is only required if you want to allow overriding existing webhooks. Choose from the list, or specify an ID using an <a href=\"https://docs.n8n.io/code/expressions/\">expression</a>.",
      "default": "",
      "options": [],
      "typeOptions": {
        "loadOptionsMethod": "getWorkspaces"
      }
    }
  ],
  "operations": [],
  "operations_by_resource": {},
  "credentials": [
    {
      "name": "asanaApi",
      "required": true,
      "displayOptions": {
        "show": {
          "authentication": [
            "accessToken"
          ]
        }
      }
    },
    {
      "name": "asanaOAuth2Api",
      "required": true,
      "displayOptions": {
        "show": {
          "authentication": [
            "oAuth2"
          ]
        }
      }
    }
  ],
  "workflow_examples": [],
  "expressions": [],
  "validation_rules": {
    "resource": {
      "required": true
    }
  },
  "type_info": {
    "authentication": {
      "type": "options",
      "displayName": "Authentication",
      "name": "authentication",
      "possibleValues": [
        {
          "value": "accessToken",
          "name": "Access Token",
          "description": ""
        },
        {
          "value": "oAuth2",
          "name": "OAuth2",
          "description": ""
        }
      ]
    },
    "resource": {
      "type": "string",
      "displayName": "Resource",
      "name": "resource"
    },
    "workspace": {
      "type": "options",
      "displayName": "Workspace Name or ID",
      "name": "workspace",
      "typeOptions": {
        "loadOptionsMethod": "getWorkspaces"
      },
      "possibleValues": []
    }
  },
  "api_patterns": {
    "http_methods": [],
    "endpoints": [],
    "headers": [],
    "query_params": []
  },
  "ui_elements": {
    "notices": [],
    "tooltips": [],
    "placeholders": [],
    "hints": []
  },
  "settings": {
    "common": {
      "notes": {
        "name": "Notes",
        "field_id": "notes",
        "type": "string",
        "default": "",
        "description": "Optional note to save with the node"
      },
      "notesInFlow": {
        "name": "Display Note in Flow?",
        "field_id": "notesInFlow",
        "type": "boolean",
        "default": false,
        "description": "If active, the note above will display in the flow as a subtitle"
      }
    },
    "note": "Trigger nodes only have common settings (notes, notesInFlow)"
  }
}